{
    "version": "0.16.103",
    "architecture": {
        "32bit": {
            "url": "https://github.com/dosco/graphjin/releases/download/v0.16.103/graphjin_0.16.103_windows_386.tar.gz",
            "bin": [
                "graphjin.exe"
            ],
            "hash": "ead1c38fc74a8053358e164693e84410340ba0e5308fd28ff7792274a5b552da"
        },
        "64bit": {
            "url": "https://github.com/dosco/graphjin/releases/download/v0.16.103/graphjin_0.16.103_windows_amd64.tar.gz",
            "bin": [
                "graphjin.exe"
            ],
            "hash": "e2671adc1884b0b9b639f941246959a65915209abc8b1a21bc819437529f1ce6"
        }
    },
    "homepage": "https://graphjin.com",
    "license": "Apache-2.0",
    "description": "Build APIs in 5 minutes. An automagical GraphQL to SQL compiler."
}