{
    "version": "0.21.7",
    "architecture": {
        "32bit": {
            "url": "https://github.com/dosco/graphjin/releases/download/v0.21.7/graphjin_0.21.7_windows_386.tar.gz",
            "bin": [
                "graphjin.exe"
            ],
            "hash": "d72786b11808b9f1a0f08dcfdf657464ede615a6190c0de12aea42e01cb29f4b"
        },
        "64bit": {
            "url": "https://github.com/dosco/graphjin/releases/download/v0.21.7/graphjin_0.21.7_windows_amd64.tar.gz",
            "bin": [
                "graphjin.exe"
            ],
            "hash": "87af09a9ffb20b6ad03e5f2cc208cf1d25aeb41b00a22347561a293bc31b903b"
        }
    },
    "homepage": "https://graphjin.com",
    "license": "Apache-2.0",
    "description": "Build APIs in 5 minutes. An automagical GraphQL to SQL compiler."
}