{
    "version": "0.16.2",
    "architecture": {
        "32bit": {
            "url": "https://github.com/dosco/graphjin/releases/download/v0.16.2/graphjin_0.16.2_Windows_i386.tar.gz",
            "bin": [
                "graphjin.exe"
            ],
            "hash": "1e6daf8823caa1f27ab5538b21ba672759f5c404ab4cedcd956eae730cd60fac"
        },
        "64bit": {
            "url": "https://github.com/dosco/graphjin/releases/download/v0.16.2/graphjin_0.16.2_Windows_x86_64.tar.gz",
            "bin": [
                "graphjin.exe"
            ],
            "hash": "6ed7306548ca7ae1b7e13c1488c58b6a920367fefe2e26dc9cd0f68b748d2737"
        }
    },
    "homepage": "https://graphjin.com",
    "license": "Apache-2.0",
    "description": "Build APIs in 5 minutes. An automagical GraphQL to SQL compiler."
}