{
    "version": "0.16.74",
    "architecture": {
        "32bit": {
            "url": "https://github.com/dosco/graphjin/releases/download/v0.16.74/graphjin_0.16.74_windows_386.tar.gz",
            "bin": [
                "graphjin.exe"
            ],
            "hash": "7412f6ba399e53f0dfcb07850e622976c96f26e182cd1f4231507bb8bf86d12e"
        },
        "64bit": {
            "url": "https://github.com/dosco/graphjin/releases/download/v0.16.74/graphjin_0.16.74_windows_amd64.tar.gz",
            "bin": [
                "graphjin.exe"
            ],
            "hash": "06d06ba9b43f5c079d290ce8a564795785aa13da53f2be5cd67d475a7234dc90"
        }
    },
    "homepage": "https://graphjin.com",
    "license": "Apache-2.0",
    "description": "Build APIs in 5 minutes. An automagical GraphQL to SQL compiler."
}